awslabs/__init__.py
awslabs/valkey_mcp_server/__init__.py
awslabs/valkey_mcp_server/context.py
awslabs/valkey_mcp_server/main.py
awslabs/valkey_mcp_server/version.py
awslabs/valkey_mcp_server/common/__init__.py
awslabs/valkey_mcp_server/common/config.py
awslabs/valkey_mcp_server/common/connection.py
awslabs/valkey_mcp_server/common/server.py
awslabs/valkey_mcp_server/tools/__init__.py
awslabs/valkey_mcp_server/tools/bitmap.py
awslabs/valkey_mcp_server/tools/hash.py
awslabs/valkey_mcp_server/tools/hyperloglog.py
awslabs/valkey_mcp_server/tools/json.py
awslabs/valkey_mcp_server/tools/list.py
awslabs/valkey_mcp_server/tools/misc.py
awslabs/valkey_mcp_server/tools/server_management.py
awslabs/valkey_mcp_server/tools/set.py
awslabs/valkey_mcp_server/tools/sorted_set.py
awslabs/valkey_mcp_server/tools/stream.py
awslabs/valkey_mcp_server/tools/string.py
awslabs_valkey_mcp_server-1.0.13.dist-info/METADATA
awslabs_valkey_mcp_server-1.0.13.dist-info/WHEEL
awslabs_valkey_mcp_server-1.0.13.dist-info/entry_points.txt
awslabs_valkey_mcp_server-1.0.13.dist-info/licenses/LICENSE
awslabs_valkey_mcp_server-1.0.13.dist-info/licenses/NOTICE
awslabs_valkey_mcp_server-1.0.13.dist-info/RECORD
